{
  "size": {
    "feature": "size",
    "type": "int",
    "keys": [
      50,
      100,
      500,
      1000,
      2000,
      4000,
      8000
    ],
    "values": {
      "50": 0,
      "100": 1,
      "500": 2,
      "1000": 3,
      "2000": 4,
      "4000": 5,
      "8000": 6,
      "max": 7
    },
    "unknown_values": false,
    "buckets": true,
    "bucket_open_right": true
  },
  "numReq": {
    "feature": "numReq",
    "type": "int",
    "keys": [
      1,
      2,
      16,
      64
    ],
    "values": {
      "1": 0,
      "2": 1,
      "16": 2,
      "64": 3,
      "max": 4
    },
    "unknown_values": false,
    "buckets": true,
    "bucket_open_right": true
  },
  "deltaLastRequest": {
    "feature": "deltaLastRequest",
    "type": "int",
    "keys": [
      10000,
      25000,
      50000,
      100000,
      150000
    ],
    "values": {
      "10000": 0,
      "25000": 1,
      "50000": 2,
      "100000": 3,
      "150000": 4,
      "max": 5
    },
    "unknown_values": false,
    "buckets": true,
    "bucket_open_right": true
  },
  "dataType": {
    "feature": "dataType",
    "type": "int",
    "keys": [
      0,
      1,
      2,
      3,
      4,
      5,
      6
    ],
    "values": {
      "0": 0,
      "1": 1,
      "2": 2,
      "3": 3,
      "4": 4,
      "5": 5,
      "6": 6
    },
    "unknown_values": false,
    "buckets": false,
    "bucket_open_right": false
  },
  "fileType": {
    "feature": "fileType",
    "type": "int",
    "keys": [
      0,
      1,
      2,
      3,
      4,
      5,
      6,
      7,
      8,
      9,
      10,
      11,
      12,
      13,
      14,
      15,
      16,
      17,
      18,
      19,
      20,
      21,
      22
    ],
    "values": {
      "0": 0,
      "1": 1,
      "2": 2,
      "3": 3,
      "4": 4,
      "5": 5,
      "6": 6,
      "7": 7,
      "8": 8,
      "9": 9,
      "10": 10,
      "11": 11,
      "12": 12,
      "13": 13,
      "14": 14,
      "15": 15,
      "16": 16,
      "17": 17,
      "18": 18,
      "19": 19,
      "20": 20,
      "21": 21,
      "22": 22
    },
    "unknown_values": false,
    "buckets": false,
    "bucket_open_right": false
  },
  "deltaHighWatermark": {
    "feature": "deltaHighWatermark",
    "type": "float",
    "keys": [
      1.0,
      5.0,
      10.0,
      20.0
    ],
    "values": {
      "1.0": 0,
      "5.0": 1,
      "10.0": 2,
      "20.0": 3,
      "max": 4
    },
    "unknown_values": false,
    "buckets": true,
    "bucket_open_right": true
  }
}
